MANIFEST.in
README.rst
setup.py
githubsurvivor/__init__.py
githubsurvivor/config.py
githubsurvivor/reporting.py
githubsurvivor/timeutils.py
githubsurvivor.egg-info/PKG-INFO
githubsurvivor.egg-info/SOURCES.txt
githubsurvivor.egg-info/dependency_links.txt
githubsurvivor.egg-info/entry_points.txt
githubsurvivor.egg-info/requires.txt
githubsurvivor.egg-info/top_level.txt
githubsurvivor/backends/__init__.py
githubsurvivor/backends/github.py
githubsurvivor/backends/jira.py
githubsurvivor/models/__init__.py
githubsurvivor/models/issue.py
githubsurvivor/models/user.py
githubsurvivor/tasks/__init__.py
githubsurvivor/tasks/sync.py
githubsurvivor/web/__init__.py
githubsurvivor/web/template.py
githubsurvivor/web/static/favicon.ico
githubsurvivor/web/static/maintenance.html
githubsurvivor/web/static/fonts/MICRO.ttf
githubsurvivor/web/static/fonts/PressStart2P.ttf
githubsurvivor/web/static/img/github/arrow-down.png
githubsurvivor/web/static/img/github/arrow-up.png
githubsurvivor/web/static/img/github/banner-end.png
githubsurvivor/web/static/img/github/banner.png
githubsurvivor/web/static/img/github/dot.png
githubsurvivor/web/static/img/github/logo.png
githubsurvivor/web/static/img/jira/arrow-down.png
githubsurvivor/web/static/img/jira/arrow-up.png
githubsurvivor/web/static/img/jira/banner-end.png
githubsurvivor/web/static/img/jira/banner.png
githubsurvivor/web/static/img/jira/dot.png
githubsurvivor/web/static/img/jira/logo.png
githubsurvivor/web/static/js/charts.js
githubsurvivor/web/static/js/dashboard.js
githubsurvivor/web/static/js/lib/jquery-1.7.2.min.js
githubsurvivor/web/static/js/lib/svg-0.10.js
githubsurvivor/web/static/styles/core.css
githubsurvivor/web/static/styles/dashboard.css
githubsurvivor/web/static/styles/report.css
githubsurvivor/web/static/styles/lib/bootstrap-responsive.css
githubsurvivor/web/static/styles/lib/bootstrap.css
githubsurvivor/web/templates/base.jinja2
githubsurvivor/web/templates/dashboard.jinja2
githubsurvivor/web/templates/old-issues.jinja2
githubsurvivor/web/templates/unassigned.jinja2
githubsurvivor/web/templates/workload.jinja2