Metadata-Version: 1.1
Name: githubsurvivor
Version: 0.0.1
Summary: A retro-style bug leaderboard
Home-page: https://github.com/99designs/githubsurvivor
Author: 99designs
Author-email: stuart.campbell@99designs.com
License: MIT
Keywords: bug dashboard leaderboard github jira
Platform: UNKNOWN
Classifier: Development Status :: 4 - Beta
